Workbook
Name TotalGeral: 'Compras e Custos'!$H$23

Sheet Compras e Custos
A1: CALCULADORA BOLEADO · COMPRAS E CUSTOS
A2: Terceira à sexta compra · Ingredientes, embalagens e utensílios
A4: Nº | B4: Compra | C4: Produto | D4: Detalhe / conteúdo | E4: Categoria | F4: Qtd | G4: Unidade | H4: Valor total (R$) | I4: Custo unitário (R$) | J4: % do total
A5: 3 | B5: Terceira compra | C5: Chocolate em pó | D5: 200 g | E5: Ingrediente | F5: 1 | G5: pct | H5: 39.9 | I5: 39.9 | J5: =IF($H$23=0,0,H5/$H$23)
A6: 3 | B6: Terceira compra | C6: Margarina | D6: 250 g | E6: Ingrediente | F6: 1 | G6: pote | H6: 6.98 | I6: 6.98 | J6: =IF($H$23=0,0,H6/$H$23)
A7: 4 | B7: Quarta compra | C7: Caixa para cento de doces | D7: 3 unidades | E7: Embalagem | F7: 3 | G7: un | H7: 10.47 | I7: 3.49 | J7: =IF($H$23=0,0,H7/$H$23)
A8: 4 | B8: Quarta compra | C8: Granulado | D8: — | E8: Ingrediente | F8: 1 | G8: pct | H8: 19.99 | I8: 19.99 | J8: =IF($H$23=0,0,H8/$H$23)
A9: 4 | B9: Quarta compra | C9: Chocolate em pó 50% | D9: — | E9: Ingrediente | F9: 1 | G9: pct | H9: 38.99 | I9: 38.99 | J9: =IF($H$23=0,0,H9/$H$23)
A10: 4 | B10: Quarta compra | C10: Leite condensado | D10: 6 unidades | E10: Ingrediente | F10: 6 | G10: lata | H10: 41.44 | I10: 6.9066667 | J10: =IF($H$23=0,0,H10/$H$23)
A11: 4 | B11: Quarta compra | C11: Creme de leite | D11: 8 unidades | E11: Ingrediente | F11: 8 | G11: cx | H11: 21.52 | I11: 2.69 | J11: =IF($H$23=0,0,H11/$H$23)
A12: 4 | B12: Quarta compra | C12: Forminha de brigadeiro | D12: 200 unidades | E12: Embalagem | F12: 200 | G12: un | H12: 6 | I12: 0.03 | J12: =IF($H$23=0,0,H12/$H$23)
A13: 5 | B13: Quinta compra | C13: Saco de confeitar | D13: 25 unidades | E13: Utensílio | F13: 25 | G13: un | H13: 13.99 | I13: 0.5596 | J13: =IF($H$23=0,0,H13/$H$23)
A14: 5 | B14: Quinta compra | C14: Coco em flocos | D14: 500 g | E14: Ingrediente | F14: 1 | G14: pct | H14: 25.99 | I14: 25.99 | J14: =IF($H$23=0,0,H14/$H$23)
A15: 5 | B15: Quinta compra | C15: Biscoito Oreo | D15: 270 g | E15: Ingrediente | F15: 1 | G15: pct | H15: 11.99 | I15: 11.99 | J15: =IF($H$23=0,0,H15/$H$23)
A16: 5 | B16: Quinta compra | C16: Pote redondo 150 ml | D16: 150 ml | E16: Embalagem | F16: 1 | G16: un | H16: 11.59 | I16: 11.59 | J16: =IF($H$23=0,0,H16/$H$23)
... A22: 6 | B22: Sexta compra | C22: Barra de chocolate | D22: — | E22: Ingrediente | F22: 1 | G22: un | H22: 30 | I22: 30 | J22: =IF($H$23=0,0,H22/$H$23)
A23: TOTAL GERAL GASTO | H23: =SUM(H5:H22) | J23: =SUM(J5:J22)
A25: Observação: 1ª e 2ª compras ainda não foram lançadas. Edite os valores na coluna H — o total e os percentuais atualizam sozinhos. Use o filtro da linha 4 para ver só uma compra ou categoria.

Sheet Resumo por compra
A1: GASTO POR COMPRA
A2: Consolidado da terceira à sexta compra
A4: Nº | B4: Compra | C4: Itens | D4: Total (R$)
A5: 3 | B5: Terceira compra | C5: =COUNTIF('Compras e Custos'!A:A,A5) | D5: =SUMIF('Compras e Custos'!A:A,A5,'Compras e Custos'!H:H)
A6: 4 | B6: Quarta compra | C6: =COUNTIF('Compras e Custos'!A:A,A6) | D6: =SUMIF('Compras e Custos'!A:A,A6,'Compras e Custos'!H:H)
A7: 5 | B7: Quinta compra | C7: =COUNTIF('Compras e Custos'!A:A,A7) | D7: =SUMIF('Compras e Custos'!A:A,A7,'Compras e Custos'!H:H)
A8: 6 | B8: Sexta compra | C8: =COUNTIF('Compras e Custos'!A:A,A8) | D8: =SUMIF('Compras e Custos'!A:A,A8,'Compras e Custos'!H:H)
A9: TOTAL GERAL | D9: =SUM(D5:D8)

Sheet Resumo por categoria
A1: GASTO POR CATEGORIA
A2: Como o dinheiro se divide entre ingredientes, embalagens e utensílios
A4: Categoria | B4: Total (R$) | C4: % do gasto
A5: Ingrediente | B5: =SUMIF('Compras e Custos'!E:E,A5,'Compras e Custos'!H:H) | C5: =IF($B$8=0,0,B5/$B$8)
A6: Embalagem | B6: =SUMIF('Compras e Custos'!E:E,A6,'Compras e Custos'!H:H) | C6: =IF($B$8=0,0,B6/$B$8)
A7: Utensílio | B7: =SUMIF('Compras e Custos'!E:E,A7,'Compras e Custos'!H:H) | C7: =IF($B$8=0,0,B7/$B$8)
A8: TOTAL | B8: =SUM(B5:B7) | C8: =SUM(C5:C7)

Sheet Estoque consolidado
A1: MESMOS PRODUTOS SOMADOS ENTRE COMPRAS
A2: Útil para ver quanto já entrou de leite condensado, creme de leite etc.
A4: Produto | B4: Categoria | C4: Qtd total | D4: Gasto total (R$) | E4: Custo médio unit. (R$)
A5: Chocolate em pó | B5: Ingrediente | C5: =SUMIF('Compras e Custos'!C:C,A5,'Compras e Custos'!F:F) | D5: =SUMIF('Compras e Custos'!C:C,A5,'Compras e Custos'!H:H) | E5: =IF(C5=0,0,D5/C5)
A6: Margarina | B6: Ingrediente | C6: =SUMIF('Compras e Custos'!C:C,A6,'Compras e Custos'!F:F) | D6: =SUMIF('Compras e Custos'!C:C,A6,'Compras e Custos'!H:H) | E6: =IF(C6=0,0,D6/C6)
A7: Caixa para cento de doces | B7: Embalagem | C7: =SUMIF('Compras e Custos'!C:C,A7,'Compras e Custos'!F:F) | D7: =SUMIF('Compras e Custos'!C:C,A7,'Compras e Custos'!H:H) | E7: =IF(C7=0,0,D7/C7)
A8: Granulado | B8: Ingrediente | C8: =SUMIF('Compras e Custos'!C:C,A8,'Compras e Custos'!F:F) | D8: =SUMIF('Compras e Custos'!C:C,A8,'Compras e Custos'!H:H) | E8: =IF(C8=0,0,D8/C8)
A9: Chocolate em pó 50% | B9: Ingrediente | C9: =SUMIF('Compras e Custos'!C:C,A9,'Compras e Custos'!F:F) | D9: =SUMIF('Compras e Custos'!C:C,A9,'Compras e Custos'!H:H) | E9: =IF(C9=0,0,D9/C9)
A10: Leite condensado | B10: Ingrediente | C10: =SUMIF('Compras e Custos'!C:C,A10,'Compras e Custos'!F:F) | D10: =SUMIF('Compras e Custos'!C:C,A10,'Compras e Custos'!H:H) | E10: =IF(C10=0,0,D10/C10)
A11: Creme de leite | B11: Ingrediente | C11: =SUMIF('Compras e Custos'!C:C,A11,'Compras e Custos'!F:F) | D11: =SUMIF('Compras e Custos'!C:C,A11,'Compras e Custos'!H:H) | E11: =IF(C11=0,0,D11/C11)
A12: Forminha de brigadeiro | B12: Embalagem | C12: =SUMIF('Compras e Custos'!C:C,A12,'Compras e Custos'!F:F) | D12: =SUMIF('Compras e Custos'!C:C,A12,'Compras e Custos'!H:H) | E12: =IF(C12=0,0,D12/C12)
A13: Saco de confeitar | B13: Utensílio | C13: =SUMIF('Compras e Custos'!C:C,A13,'Compras e Custos'!F:F) | D13: =SUMIF('Compras e Custos'!C:C,A13,'Compras e Custos'!H:H) | E13: =IF(C13=0,0,D13/C13)
A14: Coco em flocos | B14: Ingrediente | C14: =SUMIF('Compras e Custos'!C:C,A14,'Compras e Custos'!F:F) | D14: =SUMIF('Compras e Custos'!C:C,A14,'Compras e Custos'!H:H) | E14: =IF(C14=0,0,D14/C14)
A15: Biscoito Oreo | B15: Ingrediente | C15: =SUMIF('Compras e Custos'!C:C,A15,'Compras e Custos'!F:F) | D15: =SUMIF('Compras e Custos'!C:C,A15,'Compras e Custos'!H:H) | E15: =IF(C15=0,0,D15/C15)
A16: Pote redondo 150 ml | B16: Embalagem | C16: =SUMIF('Compras e Custos'!C:C,A16,'Compras e Custos'!F:F) | D16: =SUMIF('Compras e Custos'!C:C,A16,'Compras e Custos'!H:H) | E16: =IF(C16=0,0,D16/C16)
... A20: Barra de chocolate | B20: Ingrediente | C20: =SUMIF('Compras e Custos'!C:C,A20,'Compras e Custos'!F:F) | D20: =SUMIF('Compras e Custos'!C:C,A20,'Compras e Custos'!H:H) | E20: =IF(C20=0,0,D20/C20)
A21: TOTAL GERAL | D21: =SUM(D5:D20)

Sheet Como usar
A1: COMO USAR ESTA PLANILHA
A3: Tópico | B3: O que fazer
A4: Abrir no Excel | B4: Arquivo → Abrir, ou dê dois cliques neste .xlsx. No celular, use Excel ou Google Planilhas.
A5: Abrir no Google Planilhas | B5: Drive → Novo → Upload → este arquivo. Ou Planilhas → Arquivo → Importar.
A6: Lançar 1ª e 2ª compras | B6: Na aba Compras e Custos, insira linhas acima do TOTAL (antes da linha 23). Copie uma linha existente para manter fórmulas de %.
A7: Corrigir um preço | B7: Altere só a coluna H (Valor total). Custo unitário e % recalculam sozinhos.
A8: Filtrar | B8: Use as setinhas da linha 4 para ver só uma compra, só ingredientes, etc.
A9: Resumos | B9: As abas Resumo por compra, Resumo por categoria e Estoque consolidado leem a aba principal com fórmulas — não edite os totais à mão.
A10: Total atual | B10: Terceira + quarta + quinta + sexta compra = R$ 416,56.
